{"categoryPaths": ["/US"], "displayIcon": "4041472252/assets/hacker.png", "displayName": "Hacker News", "matchedQueries": ["Automatic"], "tags": ["Dynamic-test", "Dynamic US-test"], "screenId": "/screen/1f4a8b95-5ef5-4289-9602-2d6d80b1e227", "searchBarWidgets": [{"config": {"suggest": false, "searchParams": {"searchScope": ["app_search"]}, "iconTray": false, "simpleQueryList": true}, "id": "wall_searchbar", "simpleQueryListWidget": {"id": "query_list_01", "queryList": [{"query": "Taxi apps", "displayName": "Taxi", "iconUrl": "4041472252/assets/simpleQueryList/taxi.png"}, {"query": "Food apps", "displayName": "Food", "iconUrl": "4041472252/assets/simpleQueryList/restaurant.png"}, {"query": "Shopping apps", "displayName": "Shopping", "iconUrl": "4041472252/assets/simpleQueryList/shopping.png"}]}}], "version": 1453363228, "cardListWidgets": [], "id": "fb3f0dd9-ec0b-4e72-965c-122441980de4"}